{
  "journalEntries": [
    {
      "date": "",
      "conceptsCovered": "",
      "journalEntry": "",
      "mood": "",
      "id": 1
    },
    {
      "id": 2,
      "date": "August 23rd 2019",
      "concepts": "Presentation",
      "entry": "We presented our first group project. I was nervous but I think we nailed it",
      "mood": "happy"
    },
    {
      "id": 3,
      "date": "August 26th 2019",
      "concepts": "Intro to JavaScript",
      "entry": "We launched into JavaScript today.  This is going to be tough",
      "mood": "existential crisis"
    },
    {
      "date": "2019-10-06",
      "concepts": "journal",
      "entry": "I'm still working on you",
      "mood": "Mellow",
      "id": 4
    },
    {
      "date": "2019-10-07",
      "concepts": "it's the future",
      "entry": "who knows",
      "mood": "Stressed",
      "id": 5
    },
    {
      "date": "2019-10-31",
      "concepts": "halloween",
      "entry": "spooky",
      "mood": "Giddy",
      "id": 6
    }
  ]
}